hip2slack_emoji/__init__.py
hip2slack_emoji/problem.py
hip2slack_emoji-0.2.2.dist-info/LICENSE
hip2slack_emoji-0.2.2.dist-info/METADATA
hip2slack_emoji-0.2.2.dist-info/WHEEL
hip2slack_emoji-0.2.2.dist-info/entry_points.txt
hip2slack_emoji-0.2.2.dist-info/top_level.txt
hip2slack_emoji-0.2.2.dist-info/RECORD
