Metadata-Version: 2.1
Name: hip2slack-emoji
Version: 0.2.2
Summary: Importer of Hipchat emojis to Slack
Home-page: http://github.com/ivancrneto/hip2slack-emoji/
Author: Ivan Rocha
Author-email: ivan.cr.neto@gmail.com
License: MIT License
Platform: any
Classifier: Programming Language :: Python
Classifier: Development Status :: 3 - Alpha
Classifier: Natural Language :: English
Classifier: Environment :: Web Environment
Classifier: Intended Audience :: Developers
Classifier: License :: OSI Approved :: MIT License
Classifier: Operating System :: OS Independent
Classifier: Topic :: Software Development :: Libraries :: Python Modules
Classifier: Topic :: Internet :: WWW/HTTP :: Dynamic Content
Requires-Dist: splinter (==0.7.2)
Requires-Dist: requests (==2.6.2)
Requires-Dist: beautifulsoup4 (==4.6.3)
Provides-Extra: testing
Requires-Dist: pytest; extra == 'testing'
